{
  "encryptJs": true,
  "excludeScenes": [
    "9a297bec-2600-4782-ae4b-b33a303742a0",
    "140469ce-6787-4243-9f50-3a824f5847c5",
    "e14d805c-9906-46f2-9f5a-d704f113788b"
  ],
  "fb-instant-games": {},
  "includeSDKBox": false,
  "inlineSpriteFrames": true,
  "inlineSpriteFrames_native": true,
  "md5Cache": true,
  "mergeStartScene": false,
  "optimizeHotUpdate": false,
  "orientation": {
    "landscapeLeft": true,
    "landscapeRight": true,
    "portrait": false,
    "upsideDown": false
  },
  "packageName": "org.cocos2d.ssClient",
  "qqplay": {
    "REMOTE_SERVER_ROOT": "",
    "orientation": "portrait"
  },
  "startScene": "8e0a603a-14a3-4c8e-993f-fcb6cda1bff2",
  "title": "ssClient",
  "webOrientation": "landscape",
  "wechatgame": {
    "REMOTE_SERVER_ROOT": "https://www.alienidea.com/cdn/zCode/1.0.1",
    "appid": "wxc5d795237179d68b",
    "isSubdomain": false,
    "orientation": "landscape",
    "subContext": ""
  },
  "xxteaKey": "lich22-33",
  "zipCompressJs": true,
  "baidugame": {
    "appid": "testappid",
    "orientation": "portrait",
    "REMOTE_SERVER_ROOT": "",
    "subContext": ""
  },
  "android-instant": {
    "REMOTE_SERVER_ROOT": "",
    "pathPattern": "",
    "scheme": "https",
    "host": "",
    "skipRecord": false,
    "recordPath": ""
  },
  "appBundle": false
}